branchmgr/__init__.py
branchmgr/main.py
branchmgr-1.0.0.dist-info/DESCRIPTION.rst
branchmgr-1.0.0.dist-info/METADATA
branchmgr-1.0.0.dist-info/RECORD
branchmgr-1.0.0.dist-info/WHEEL
branchmgr-1.0.0.dist-info/entry_points.txt
branchmgr-1.0.0.dist-info/metadata.json
branchmgr-1.0.0.dist-info/top_level.txt
