Metadata-Version: 2.0
Name: branchmgr
Version: 1.0.0
Summary: A tool for managing GitHub branch permissions.
Home-page: http://python-hyper.org
Author: Cory Benfield
Author-email: cory@lukasa.co.uk
License: MIT License
Platform: UNKNOWN
Classifier: Development Status :: 3 - Alpha
Classifier: Intended Audience :: Developers
Classifier: License :: OSI Approved :: MIT License
Classifier: Programming Language :: Python
Classifier: Programming Language :: Python :: 3.6
Classifier: Programming Language :: Python :: Implementation :: CPython
Requires-Dist: click
Requires-Dist: gidgethub
Requires-Dist: treq
Requires-Dist: twisted[tls]
